macocr/__init__.py
macocr/main.py
macocr-0.1.7.dist-info/METADATA
macocr-0.1.7.dist-info/WHEEL
macocr-0.1.7.dist-info/entry_points.txt
macocr-0.1.7.dist-info/licenses/LICENSE
macocr-0.1.7.dist-info/RECORD
