Metadata-Version: 2.4
Name: macocr
Version: 0.1.7
Summary: macocr is a python script for OCR on macOS
Project-URL: Homepage, https://github.com/rioriost/homebrew-macocr
Project-URL: Issues, https://github.com/rioriost/homebrew-macocr/issues
Author-email: Rio Fujita <rifujita@microsoft.com>
License: MIT License
License-File: LICENSE
Requires-Python: >=3.11
Requires-Dist: ocrmac>=1.0.0
Requires-Dist: pillow-heif>=1.1.1
Requires-Dist: python-magic>=0.4.27
